[
   {
        "title": "Burp Suite - the Best Security Scanner",
        "category": "Scanner",
        "url": "https://portswigger.net/burp/communitydownload"
    },
    {
        "title": "ZAP - Security Scanner",
        "category": "Scanner",
        "url": "https://www.zaproxy.org/"
    },
    {
        "title": "Security Scanner",
        "category": "Scanner",
        "url": "https://portswigger.net/burp/communitydownload"
    },
    {
        "title": "Tool Scanner",
        "category": "Scanner",
        "url": "https://portswigger.net/burp/communitydownload"
    }
]
